{"categories":[{"id":"1","name":"Productivity","description":"Prompts related to time management and efficiency","icon":"fa-clock","color":"#FF5733","promptCount":25,"sortOrder":1,"filePathName":"data.json"},{"id":"2","name":"Marketing","description":"Prompts related to Marketing","icon":"fa-clock","color":"#FF5733","promptCount":25,"sortOrder":1,"filePathName":"marketing.json"},{"id":"3","name":"Development","description":"Prompts related to Developer","icon":"fa-clock","color":"#FF5733","promptCount":25,"sortOrder":1,"filePathName":"development.json"},{"id":"4","name":"Asp Net Blazor","description":"Prompts Related to balzor web Application","icon":"fa-clock","color":"#3258b8ff","promptCount":25,"sortOrder":2,"filePathName":"blazor.json"},{"id":"5","name":"Generate Image","description":"Prompts Related to Image Generation","icon":"fa-clock","color":"#3258b8ff","promptCount":25,"sortOrder":2,"filePathName":"image.json"}]}